[
  {
    "timestamp": "2025-06-21T05:00:00",
    "total_price": 1465805254,
    "item_count": 278,
    "average_price": 5272680,
    "original_points": 278
  },
  {
    "timestamp": "2025-06-21T06:00:00",
    "total_price": 1463266146,
    "item_count": 278,
    "average_price": 5263547,
    "original_points": 278
  },
  {
    "timestamp": "2025-06-21T07:00:00",
    "total_price": 1462295169,
    "item_count": 278,
    "average_price": 5260054,
    "original_points": 278
  },
  {
    "timestamp": "2025-06-21T10:00:00",
    "total_price": 1456256557,
    "item_count": 278,
    "average_price": 5238332,
    "original_points": 278
  },
  {
    "timestamp": "2025-06-21T12:00:00",
    "total_price": 1451886770,
    "item_count": 278,
    "average_price": 5222614,
    "original_points": 278
  },
  {
    "timestamp": "2025-06-21T13:00:00",
    "total_price": 1459948686,
    "item_count": 278,
    "average_price": 5251613,
    "original_points": 278
  },
  {
    "timestamp": "2025-06-21T14:00:00",
    "total_price": 1465620624,
    "item_count": 278,
    "average_price": 5272016,
    "original_points": 278
  },
  {
    "timestamp": "2025-06-21T16:00:00",
    "total_price": 1463813503,
    "item_count": 278,
    "average_price": 5265516,
    "original_points": 278
  },
  {
    "timestamp": "2025-06-21T17:00:00",
    "total_price": 1460222503,
    "item_count": 278,
    "average_price": 5252598,
    "original_points": 278
  },
  {
    "timestamp": "2025-06-21T18:00:00",
    "total_price": 1482192136,
    "item_count": 279,
    "average_price": 5312516,
    "original_points": 279
  },
  {
    "timestamp": "2025-06-21T19:00:00",
    "total_price": 1490492388,
    "item_count": 279,
    "average_price": 5342266,
    "original_points": 279
  },
  {
    "timestamp": "2025-06-21T21:00:00",
    "total_price": 1505576952,
    "item_count": 279,
    "average_price": 5396333,
    "original_points": 279
  },
  {
    "timestamp": "2025-06-21T22:00:00",
    "total_price": 1500916302,
    "item_count": 279,
    "average_price": 5379628,
    "original_points": 279
  },
  {
    "timestamp": "2025-06-22T00:00:00",
    "total_price": 1520862446,
    "item_count": 279,
    "average_price": 5451119,
    "original_points": 279
  },
  {
    "timestamp": "2025-06-22T01:00:00",
    "total_price": 1525221732,
    "item_count": 279,
    "average_price": 5466744,
    "original_points": 279
  },
  {
    "timestamp": "2025-06-22T02:00:00",
    "total_price": 1525171039,
    "item_count": 279,
    "average_price": 5466562,
    "original_points": 279
  },
  {
    "timestamp": "2025-06-22T03:00:00",
    "total_price": 1521389556,
    "item_count": 279,
    "average_price": 5453009,
    "original_points": 279
  },
  {
    "timestamp": "2025-06-22T05:00:00",
    "total_price": 1520151557,
    "item_count": 279,
    "average_price": 5448571,
    "original_points": 279
  },
  {
    "timestamp": "2025-06-22T06:00:00",
    "total_price": 1530300223,
    "item_count": 279,
    "average_price": 5484947,
    "original_points": 279
  },
  {
    "timestamp": "2025-06-22T07:00:00",
    "total_price": 1527602802,
    "item_count": 279,
    "average_price": 5475278,
    "original_points": 279
  },
  {
    "timestamp": "2025-06-22T10:00:00",
    "total_price": 1524936493,
    "item_count": 280,
    "average_price": 5446201,
    "original_points": 280
  },
  {
    "timestamp": "2025-06-22T12:00:00",
    "total_price": 1518021880,
    "item_count": 280,
    "average_price": 5421506,
    "original_points": 280
  },
  {
    "timestamp": "2025-06-22T14:00:00",
    "total_price": 1533443938,
    "item_count": 280,
    "average_price": 5476585,
    "original_points": 280
  },
  {
    "timestamp": "2025-06-22T15:00:00",
    "total_price": 1551578807,
    "item_count": 280,
    "average_price": 5541352,
    "original_points": 280
  },
  {
    "timestamp": "2025-06-22T16:00:00",
    "total_price": 1580972905,
    "item_count": 280,
    "average_price": 5646331,
    "original_points": 280
  },
  {
    "timestamp": "2025-06-22T17:00:00",
    "total_price": 1638058595,
    "item_count": 280,
    "average_price": 5850209,
    "original_points": 280
  },
  {
    "timestamp": "2025-06-22T19:00:00",
    "total_price": 1660085594,
    "item_count": 280,
    "average_price": 5928877,
    "original_points": 280
  },
  {
    "timestamp": "2025-06-22T20:00:00",
    "total_price": 1671031796,
    "item_count": 280,
    "average_price": 5967970,
    "original_points": 280
  },
  {
    "timestamp": "2025-06-22T22:00:00",
    "total_price": 1685610387,
    "item_count": 280,
    "average_price": 6020037,
    "original_points": 280
  },
  {
    "timestamp": "2025-06-22T23:00:00",
    "total_price": 1731487766,
    "item_count": 280,
    "average_price": 6183884,
    "original_points": 280
  },
  {
    "timestamp": "2025-06-23T01:00:00",
    "total_price": 1740308313,
    "item_count": 280,
    "average_price": 6215386,
    "original_points": 280
  },
  {
    "timestamp": "2025-06-23T03:00:00",
    "total_price": 1106939521,
    "item_count": 280,
    "average_price": 3953355,
    "original_points": 280
  },
  {
    "timestamp": "2025-06-23T04:00:00",
    "total_price": 1061153089,
    "item_count": 280,
    "average_price": 3789832,
    "original_points": 280
  },
  {
    "timestamp": "2025-06-23T05:00:00",
    "total_price": 1071606954,
    "item_count": 280,
    "average_price": 3827167,
    "original_points": 280
  },
  {
    "timestamp": "2025-06-23T06:00:00",
    "total_price": 1066961589,
    "item_count": 280,
    "average_price": 3810577,
    "original_points": 280
  },
  {
    "timestamp": "2025-06-23T07:00:00",
    "total_price": 1071078428,
    "item_count": 280,
    "average_price": 3825280,
    "original_points": 280
  },
  {
    "timestamp": "2025-06-23T10:00:00",
    "total_price": 1067263399,
    "item_count": 280,
    "average_price": 3811654,
    "original_points": 280
  },
  {
    "timestamp": "2025-06-23T12:00:00",
    "total_price": 1049877012,
    "item_count": 280,
    "average_price": 3749560,
    "original_points": 280
  },
  {
    "timestamp": "2025-06-23T14:00:00",
    "total_price": 1035024687,
    "item_count": 280,
    "average_price": 3696516,
    "original_points": 280
  },
  {
    "timestamp": "2025-06-23T15:00:00",
    "total_price": 1021038336,
    "item_count": 280,
    "average_price": 3646565,
    "original_points": 280
  },
  {
    "timestamp": "2025-06-23T16:00:00",
    "total_price": 1036051084,
    "item_count": 280,
    "average_price": 3700182,
    "original_points": 280
  },
  {
    "timestamp": "2025-06-23T18:00:00",
    "total_price": 1011879017,
    "item_count": 280,
    "average_price": 3613853,
    "original_points": 280
  },
  {
    "timestamp": "2025-06-23T19:00:00",
    "total_price": 964366960,
    "item_count": 280,
    "average_price": 3444167,
    "original_points": 280
  },
  {
    "timestamp": "2025-06-23T20:00:00",
    "total_price": 965366281,
    "item_count": 280,
    "average_price": 3447736,
    "original_points": 280
  },
  {
    "timestamp": "2025-06-23T21:00:00",
    "total_price": 971760970,
    "item_count": 280,
    "average_price": 3470574,
    "original_points": 280
  },
  {
    "timestamp": "2025-06-23T23:00:00",
    "total_price": 947258997,
    "item_count": 280,
    "average_price": 3383067,
    "original_points": 280
  },
  {
    "timestamp": "2025-06-24T00:00:00",
    "total_price": 970012708,
    "item_count": 280,
    "average_price": 3464331,
    "original_points": 280
  },
  {
    "timestamp": "2025-06-24T01:00:00",
    "total_price": 938206966,
    "item_count": 280,
    "average_price": 3350739,
    "original_points": 280
  }
]