[
  {
    "timestamp": "2025-06-18T23:00:00",
    "total_price": 1354271772,
    "item_count": 278,
    "average_price": 4871481,
    "original_points": 278
  },
  {
    "timestamp": "2025-06-19T01:00:00",
    "total_price": 1354187966,
    "item_count": 278,
    "average_price": 4871179,
    "original_points": 278
  },
  {
    "timestamp": "2025-06-19T02:00:00",
    "total_price": 1353532741,
    "item_count": 278,
    "average_price": 4868822,
    "original_points": 278
  },
  {
    "timestamp": "2025-06-19T04:00:00",
    "total_price": 1349327735,
    "item_count": 278,
    "average_price": 4853696,
    "original_points": 278
  },
  {
    "timestamp": "2025-06-19T05:00:00",
    "total_price": 1351193546,
    "item_count": 278,
    "average_price": 4860408,
    "original_points": 278
  },
  {
    "timestamp": "2025-06-19T06:00:00",
    "total_price": 1353495191,
    "item_count": 278,
    "average_price": 4868687,
    "original_points": 278
  },
  {
    "timestamp": "2025-06-19T08:00:00",
    "total_price": 1353495191,
    "item_count": 278,
    "average_price": 4868687,
    "original_points": 278
  },
  {
    "timestamp": "2025-06-19T10:00:00",
    "total_price": 1353495191,
    "item_count": 278,
    "average_price": 4868687,
    "original_points": 278
  },
  {
    "timestamp": "2025-06-19T12:00:00",
    "total_price": 1348839293,
    "item_count": 278,
    "average_price": 4851939,
    "original_points": 278
  },
  {
    "timestamp": "2025-06-19T14:00:00",
    "total_price": 1340973814,
    "item_count": 278,
    "average_price": 4823646,
    "original_points": 278
  },
  {
    "timestamp": "2025-06-19T15:00:00",
    "total_price": 1337886245,
    "item_count": 278,
    "average_price": 4812540,
    "original_points": 278
  },
  {
    "timestamp": "2025-06-19T16:00:00",
    "total_price": 1339052833,
    "item_count": 278,
    "average_price": 4816736,
    "original_points": 278
  },
  {
    "timestamp": "2025-06-19T18:00:00",
    "total_price": 1333271383,
    "item_count": 278,
    "average_price": 4795940,
    "original_points": 278
  },
  {
    "timestamp": "2025-06-19T19:00:00",
    "total_price": 1332223253,
    "item_count": 278,
    "average_price": 4792169,
    "original_points": 278
  },
  {
    "timestamp": "2025-06-19T20:00:00",
    "total_price": 1342389735,
    "item_count": 278,
    "average_price": 4828740,
    "original_points": 278
  },
  {
    "timestamp": "2025-06-19T22:00:00",
    "total_price": 1407047358,
    "item_count": 278,
    "average_price": 5061321,
    "original_points": 278
  },
  {
    "timestamp": "2025-06-19T23:00:00",
    "total_price": 1412238891,
    "item_count": 278,
    "average_price": 5079996,
    "original_points": 278
  },
  {
    "timestamp": "2025-06-20T01:00:00",
    "total_price": 1423776064,
    "item_count": 278,
    "average_price": 5121496,
    "original_points": 278
  },
  {
    "timestamp": "2025-06-20T02:00:00",
    "total_price": 1426130474,
    "item_count": 278,
    "average_price": 5129965,
    "original_points": 278
  },
  {
    "timestamp": "2025-06-20T04:00:00",
    "total_price": 1426954887,
    "item_count": 278,
    "average_price": 5132931,
    "original_points": 278
  },
  {
    "timestamp": "2025-06-20T05:00:00",
    "total_price": 1454564051,
    "item_count": 278,
    "average_price": 5232244,
    "original_points": 278
  },
  {
    "timestamp": "2025-06-20T06:00:00",
    "total_price": 1452161320,
    "item_count": 278,
    "average_price": 5223601,
    "original_points": 278
  },
  {
    "timestamp": "2025-06-20T07:00:00",
    "total_price": 1463762543,
    "item_count": 278,
    "average_price": 5265332,
    "original_points": 278
  },
  {
    "timestamp": "2025-06-20T10:00:00",
    "total_price": 1464803543,
    "item_count": 278,
    "average_price": 5269077,
    "original_points": 278
  },
  {
    "timestamp": "2025-06-20T12:00:00",
    "total_price": 1457027863,
    "item_count": 278,
    "average_price": 5241107,
    "original_points": 278
  },
  {
    "timestamp": "2025-06-20T13:00:00",
    "total_price": 1446042632,
    "item_count": 278,
    "average_price": 5201592,
    "original_points": 278
  },
  {
    "timestamp": "2025-06-20T14:00:00",
    "total_price": 1443126082,
    "item_count": 278,
    "average_price": 5191101,
    "original_points": 278
  },
  {
    "timestamp": "2025-06-20T16:00:00",
    "total_price": 1437890184,
    "item_count": 278,
    "average_price": 5172266,
    "original_points": 278
  },
  {
    "timestamp": "2025-06-20T17:00:00",
    "total_price": 1432306477,
    "item_count": 278,
    "average_price": 5152181,
    "original_points": 278
  },
  {
    "timestamp": "2025-06-20T18:00:00",
    "total_price": 1441205379,
    "item_count": 278,
    "average_price": 5184192,
    "original_points": 278
  },
  {
    "timestamp": "2025-06-20T20:00:00",
    "total_price": 1451126617,
    "item_count": 278,
    "average_price": 5219879,
    "original_points": 278
  },
  {
    "timestamp": "2025-06-20T21:00:00",
    "total_price": 1443717873,
    "item_count": 278,
    "average_price": 5193229,
    "original_points": 278
  },
  {
    "timestamp": "2025-06-20T23:00:00",
    "total_price": 1464389298,
    "item_count": 278,
    "average_price": 5267587,
    "original_points": 278
  },
  {
    "timestamp": "2025-06-21T00:00:00",
    "total_price": 1457102415,
    "item_count": 278,
    "average_price": 5241375,
    "original_points": 278
  },
  {
    "timestamp": "2025-06-21T01:00:00",
    "total_price": 1458485547,
    "item_count": 278,
    "average_price": 5246350,
    "original_points": 278
  },
  {
    "timestamp": "2025-06-21T02:00:00",
    "total_price": 1466774530,
    "item_count": 278,
    "average_price": 5276167,
    "original_points": 278
  },
  {
    "timestamp": "2025-06-21T04:00:00",
    "total_price": 1469651560,
    "item_count": 278,
    "average_price": 5286516,
    "original_points": 278
  },
  {
    "timestamp": "2025-06-21T05:00:00",
    "total_price": 1465805254,
    "item_count": 278,
    "average_price": 5272680,
    "original_points": 278
  },
  {
    "timestamp": "2025-06-21T06:00:00",
    "total_price": 1463266146,
    "item_count": 278,
    "average_price": 5263547,
    "original_points": 278
  },
  {
    "timestamp": "2025-06-21T07:00:00",
    "total_price": 1462295169,
    "item_count": 278,
    "average_price": 5260054,
    "original_points": 278
  },
  {
    "timestamp": "2025-06-21T10:00:00",
    "total_price": 1456256557,
    "item_count": 278,
    "average_price": 5238332,
    "original_points": 278
  },
  {
    "timestamp": "2025-06-21T12:00:00",
    "total_price": 1451886770,
    "item_count": 278,
    "average_price": 5222614,
    "original_points": 278
  },
  {
    "timestamp": "2025-06-21T13:00:00",
    "total_price": 1459948686,
    "item_count": 278,
    "average_price": 5251613,
    "original_points": 278
  },
  {
    "timestamp": "2025-06-21T14:00:00",
    "total_price": 1465620624,
    "item_count": 278,
    "average_price": 5272016,
    "original_points": 278
  },
  {
    "timestamp": "2025-06-21T16:00:00",
    "total_price": 1463813503,
    "item_count": 278,
    "average_price": 5265516,
    "original_points": 278
  },
  {
    "timestamp": "2025-06-21T17:00:00",
    "total_price": 1460222503,
    "item_count": 278,
    "average_price": 5252598,
    "original_points": 278
  },
  {
    "timestamp": "2025-06-21T18:00:00",
    "total_price": 1482192136,
    "item_count": 279,
    "average_price": 5312516,
    "original_points": 279
  },
  {
    "timestamp": "2025-06-21T19:00:00",
    "total_price": 1490492388,
    "item_count": 279,
    "average_price": 5342266,
    "original_points": 279
  }
]