[
  {
    "timestamp": "2025-07-05T12:00:00",
    "total_price": 816771044,
    "item_count": 280,
    "average_price": 2917039,
    "original_points": 280
  },
  {
    "timestamp": "2025-07-06T00:00:00",
    "total_price": 818379221,
    "item_count": 280,
    "average_price": 2922782,
    "original_points": 5320
  },
  {
    "timestamp": "2025-07-06T12:00:00",
    "total_price": 800727746,
    "item_count": 280,
    "average_price": 2859741,
    "original_points": 5320
  },
  {
    "timestamp": "2025-07-07T00:00:00",
    "total_price": 805506594,
    "item_count": 280,
    "average_price": 2876809,
    "original_points": 5320
  },
  {
    "timestamp": "2025-07-07T12:00:00",
    "total_price": 797776797,
    "item_count": 280,
    "average_price": 2849202,
    "original_points": 560
  }
]